README
setup.cfg
setup.py
pyramid_game_offers/__init__.py
pyramid_game_offers/trialpay.py
pyramid_game_offers.egg-info/PKG-INFO
pyramid_game_offers.egg-info/SOURCES.txt
pyramid_game_offers.egg-info/dependency_links.txt
pyramid_game_offers.egg-info/requires.txt
pyramid_game_offers.egg-info/top_level.txt