Metadata-Version: 1.0
Name: pyramid-game-offers
Version: 0.2.13
Summary: Pyramid resources and views for monetization providers
Home-page: UNKNOWN
Author: UNKNOWN
Author-email: UNKNOWN
License: UNKNOWN
Platform: UNKNOWN
